napari_openfibsem/__init__.py
napari_openfibsem/_version.py
napari_openfibsem/app.py
napari_openfibsem/napari.yaml
napari_openfibsem-0.1.5.dist-info/LICENSE
napari_openfibsem-0.1.5.dist-info/METADATA
napari_openfibsem-0.1.5.dist-info/WHEEL
napari_openfibsem-0.1.5.dist-info/entry_points.txt
napari_openfibsem-0.1.5.dist-info/top_level.txt
napari_openfibsem-0.1.5.dist-info/RECORD
