Metadata-Version: 2.1
Name: napari-openfibsem
Version: 0.1.5
Summary: OpenFIBSEM Applications
Home-page: https://github.com/DeMarcoLab/napari-openfibsem
Author: Patrick Cleeve
Author-email: patrick.cleeve@monash.edu
License: MIT
Project-URL: Bug Tracker, https://github.com/DeMarcoLab/napari-openfibsem/issues
Project-URL: Documentation, https://github.com/DeMarcoLab/napari-openfibsem#README.md
Project-URL: Source Code, https://github.com/DeMarcoLab/napari-openfibsem
Project-URL: User Support, https://github.com/DeMarcoLab/napari-openfibsem/issues
Classifier: Development Status :: 2 - Pre-Alpha
Classifier: Framework :: napari
Classifier: Intended Audience :: Developers
Classifier: License :: OSI Approved :: MIT License
Classifier: Operating System :: OS Independent
Classifier: Programming Language :: Python
Classifier: Programming Language :: Python :: 3
Classifier: Programming Language :: Python :: 3 :: Only
Classifier: Programming Language :: Python :: 3.8
Classifier: Programming Language :: Python :: 3.9
Classifier: Programming Language :: Python :: 3.10
Classifier: Topic :: Scientific/Engineering :: Image Processing
Requires-Python: >=3.9
License-File: LICENSE
Requires-Dist: fibsem >=0.3.2a1
Requires-Dist: autolamella >=0.3.2a1
Provides-Extra: testing
Requires-Dist: tox ; extra == 'testing'
Requires-Dist: pytest ; extra == 'testing'
Requires-Dist: pytest-cov ; extra == 'testing'
Requires-Dist: pytest-qt ; extra == 'testing'
Requires-Dist: napari ; extra == 'testing'
Requires-Dist: pyqt5 ; extra == 'testing'
